<annotation>
	<folder>train</folder>
	<filename>image17.jpg</filename>
	<path>I:\data\car_dent\train\image17.jpg</path>
	<source>
		<database>Unknown</database>
	</source>
	<size>
		<width>1500</width>
		<height>1225</height>
		<depth>3</depth>
	</size>
	<segmented>0</segmented>
	<object>
		<name>car_dent</name>
		<pose>Unspecified</pose>
		<truncated>0</truncated>
		<difficult>0</difficult>
		<bndbox>
			<xmin>222</xmin>
			<ymin>182</ymin>
			<xmax>881</xmax>
			<ymax>680</ymax>
		</bndbox>
	</object>
</annotation>
